brasil.gov.vlibrasnews-1.0b1-py2.7-nspkg.pth
brasil/gov/vlibrasnews/__init__.py
brasil/gov/vlibrasnews/api.py
brasil/gov/vlibrasnews/behaviors.py
brasil/gov/vlibrasnews/behaviors.zcml
brasil/gov/vlibrasnews/config.py
brasil/gov/vlibrasnews/configure.zcml
brasil/gov/vlibrasnews/controlpanel.py
brasil/gov/vlibrasnews/interfaces.py
brasil/gov/vlibrasnews/logger.py
brasil/gov/vlibrasnews/profiles.zcml
brasil/gov/vlibrasnews/setuphandlers.py
brasil/gov/vlibrasnews/subscribers.py
brasil/gov/vlibrasnews/subscribers.zcml
brasil/gov/vlibrasnews/testing.py
brasil/gov/vlibrasnews/Extensions/Install.py
brasil/gov/vlibrasnews/Extensions/__init__.py
brasil/gov/vlibrasnews/browser/__init__.py
brasil/gov/vlibrasnews/browser/configure.zcml
brasil/gov/vlibrasnews/browser/vlibrasnews.pt
brasil/gov/vlibrasnews/browser/vlibrasnews.py
brasil/gov/vlibrasnews/locales/brasil.gov.vlibrasnews.pot
brasil/gov/vlibrasnews/locales/manual.pot
brasil/gov/vlibrasnews/locales/plone.pot
brasil/gov/vlibrasnews/locales/es/LC_MESSAGES/brasil.gov.vlibrasnews.po
brasil/gov/vlibrasnews/locales/es/LC_MESSAGES/plone.po
brasil/gov/vlibrasnews/locales/pt_BR/LC_MESSAGES/brasil.gov.vlibrasnews.po
brasil/gov/vlibrasnews/locales/pt_BR/LC_MESSAGES/plone.po
brasil/gov/vlibrasnews/profiles/default/browserlayer.xml
brasil/gov/vlibrasnews/profiles/default/controlpanel.xml
brasil/gov/vlibrasnews/profiles/default/cssregistry.xml
brasil/gov/vlibrasnews/profiles/default/jsregistry.xml
brasil/gov/vlibrasnews/profiles/default/metadata.xml
brasil/gov/vlibrasnews/profiles/default/registry.xml
brasil/gov/vlibrasnews/profiles/uninstall/registry.xml
brasil/gov/vlibrasnews/static/main.css
brasil/gov/vlibrasnews/static/main.js
brasil/gov/vlibrasnews/static/vlibrasnews-icon.png
brasil/gov/vlibrasnews/static/vlibrasnews-icon.svg
brasil/gov/vlibrasnews/tests/__init__.py
brasil/gov/vlibrasnews/tests/test_controlpanel.py
brasil/gov/vlibrasnews/tests/test_robot.py
brasil.gov.vlibrasnews-1.0b1.dist-info/DESCRIPTION.rst
brasil.gov.vlibrasnews-1.0b1.dist-info/METADATA
brasil.gov.vlibrasnews-1.0b1.dist-info/RECORD
brasil.gov.vlibrasnews-1.0b1.dist-info/WHEEL
brasil.gov.vlibrasnews-1.0b1.dist-info/entry_points.txt
brasil.gov.vlibrasnews-1.0b1.dist-info/metadata.json
brasil.gov.vlibrasnews-1.0b1.dist-info/namespace_packages.txt
brasil.gov.vlibrasnews-1.0b1.dist-info/top_level.txt
