Metadata-Version: 2.0
Name: brasil.gov.vlibrasnews
Version: 1.0b1
Summary: .gov.br: Tradução de Português para Libras
Home-page: https://github.com/plonegovbr/brasil.gov.vlibrasnews
Author: Simples Consultoria
Author-email: produtos@simplesconsultoria.com.br
License: UNKNOWN
Platform: UNKNOWN
Classifier: Development Status :: 3 - Alpha
Classifier: Environment :: Web Environment
Classifier: Framework :: Plone
Classifier: Framework :: Plone :: 4.3
Classifier: Framework :: Plone :: 5.0
Classifier: Intended Audience :: System Administrators
Classifier: License :: OSI Approved :: GNU General Public License v2 (GPLv2)
Classifier: Operating System :: OS Independent
Classifier: Programming Language :: Python
Classifier: Programming Language :: Python :: 2.7
Classifier: Topic :: Software Development :: Libraries :: Python Modules
Requires-Dist: Products.CMFPlone (>=4.3)
Requires-Dist: Products.GenericSetup
Requires-Dist: plone.api
Requires-Dist: plone.app.layout
Requires-Dist: plone.app.registry
Requires-Dist: plone.autoform
Requires-Dist: plone.behavior
Requires-Dist: plone.dexterity
Requires-Dist: plone.memoize
Requires-Dist: plone.supermodel
Requires-Dist: requests
Requires-Dist: setuptools
Requires-Dist: zope.component
Requires-Dist: zope.i18nmessageid
Requires-Dist: zope.interface
Requires-Dist: zope.schema
Provides-Extra: test
Requires-Dist: AccessControl; extra == 'test'
Requires-Dist: httmock; extra == 'test'
Requires-Dist: mock; extra == 'test'
Requires-Dist: plone.app.contenttypes; extra == 'test'
Requires-Dist: plone.app.robotframework; extra == 'test'
Requires-Dist: plone.app.testing[robot]; extra == 'test'
Requires-Dist: plone.app.textfield; extra == 'test'
Requires-Dist: plone.browserlayer; extra == 'test'
Requires-Dist: plone.registry; extra == 'test'
Requires-Dist: plone.testing; extra == 'test'
Requires-Dist: robotsuite; extra == 'test'
Requires-Dist: zope.component; extra == 'test'
